Vivado/Vivado.srcs/sources_1/new/program_memory2.v
`timescale 1ns / 1ps
//////////////////////////////////////////////////////////////////////////////////
// Company: 
// Engineer: 
// 
// Create Date: 03/05/2023 04:39:44 PM
// Design Name: 
// Module Name: program_memory
// Project Name: 
// Target Devices: 
// Tool Versions: 
// Description: 
// 
// Dependencies: 
// 
// Revision:
// Revision 0.01 - File Created
// Additional Comments:
// 
//////////////////////////////////////////////////////////////////////////////////

// Opcodes
`define OP_ADD      4'b0000
`define OP_MUL      4'b0010
`define OP_MOV      4'b0100
`define OP_NOP      4'b0111
`define OP_LD_IMM   6'b100000
`define OP_CMP_IMM  6'b100011
`define OP_DEC      6'b100101
`define OP_INPUT    6'b100110
`define OP_OUTPUT   6'b100111
`define OP_BRA      6'b101010
`define OP_BHI      6'b101100
`define OP_BEQ      6'b101101

module program_memory2(
    input  [7:0] address_bus,
    output [7:0] data_bus,
    input  reset,
    input program_clk
    );
    
    reg [7:0] program_rom [255:0];
    assign data_bus = program_rom[address_bus];
    
    always @(posedge(program_clk))
        if (reset == 0) begin
            program_rom[ 0] <= {`OP_INPUT,2'd0};        //start:     INPUT R0
            program_rom[ 1] <= {`OP_CMP_IMM,2'd0};      //           CMP R0, #1
            program_rom[ 2] <= 8'd1;                    //           ^^^ #1
            program_rom[ 3] <= {`OP_BHI,2'b00};         //           BHI init
            program_rom[ 4] <= 8'd9;                    //           ^^^ init (9) 
            program_rom[ 5] <= {`OP_MOV,2'd1,2'd0};     //           MOV R1,R0 
            program_rom[ 6] <= {`OP_OUTPUT,2'd1};       //end:       OUTPUT R1
            program_rom[ 7] <= {`OP_BRA,2'b00};         //           BRA start
            program_rom[ 8] <= 8'd0;                    //           ^^^start(0)
            program_rom[ 9] <= {`OP_LD_IMM,2'd1};       //init:      LD R1, #0
            program_rom[10] <= 8'd0;                    //           ^^^#0
            program_rom[11] <= {`OP_LD_IMM,2'd2};       //           LD R2, #1
            program_rom[12] <= 8'd1;                    //           ^^^#1
            program_rom[13] <= {`OP_CMP_IMM,2'd0};      //loop:      CMP R0, #0
            program_rom[14] <= 8'd0;                    //           ^^^#0
            program_rom[15] <= {`OP_BEQ,2'b00};         //           BEQ end
            program_rom[16] <= 8'd6;                    //           ^^^end(6)
            program_rom[17] <= {`OP_MOV,2'd3,2'd1};     //           MOV R3, R1
            program_rom[18] <= {`OP_ADD,2'd3,2'd2};     //           ADD R3, R2
            program_rom[19] <= {`OP_MOV,2'd1,2'd2};     //           MOV R1, R2
            program_rom[20] <= {`OP_MOV,2'd2,2'd3};     //           MOV R2, R3
            program_rom[21] <= {`OP_DEC,2'd0};          //           DEC R0
            program_rom[22] <= {`OP_BRA,2'b00};         //           BRA loop
            program_rom[23] <= 8'd13;                   //           ^^^loop(13)
            program_rom[24] <= 8'b0111_0000; // NOP
            program_rom[25] <= 8'b0111_0000; // NOP
            program_rom[26] <= 8'b0111_0000; // NOP
            program_rom[27] <= 8'b0111_0000; // NOP
            program_rom[28] <= 8'b0111_0000; // NOP
            program_rom[29] <= 8'b0111_0000; // NOP
            program_rom[30] <= 8'b0111_0000; // NOP
            program_rom[31] <= 8'b0111_0000; // NOP
     end
endmodule

Vivado/Vivado.srcs/sources_1/new/MCP.v
`timescale 1ns / 1ps
//////////////////////////////////////////////////////////////////////////////////
// Company: 
// Engineer: Le Phu Thuan
// 
// Create Date: 03/05/2023 03:06:46 PM
// Design Name: 
// Module Name: mcp
// Project Name: Simple Microprocessor
// Target Devices: Basys3
// Tool Versions: Vivado 2022.2
// Description: 
// 
// Dependencies: 
// 
// Revision:
// Revision 0.01 - File Created
// Additional Comments:
// 
//////////////////////////////////////////////////////////////////////////////////

// Opcodes
`define ADD_REG  6'b000000
`define MUL      6'b000010
`define MOV      6'b000100
`define NOP      6'b000111
`define LD_IMM   6'b100000
`define CMP_IMM  6'b100011
`define DEC      6'b100101
`define INPUT    6'b100110
`define OUTPUT   6'b100111
`define BRA      6'b101010
`define BHI      6'b101100
`define BEQ      6'b101101

// Control Logic States, One-Hot Encoded
`define FETCH      3'b001
`define EXECUTE    3'b010
`define WRITE_BACK 3'b100

module mcp(
    input clk,
    input reset,
    input  [7:0]  in_port_0,
    input  [7:0]  in_port_1,
    input  [7:0]  in_port_2,
    input  [7:0]  in_port_3,
    output [7:0] out_port_0,
    output [7:0] out_port_1,
    output [7:0] out_port_2,
    output [7:0] out_port_3,
    output reg [3:0] in_strobe,
    output reg [3:0] out_strobe,
    input  [7:0] inst_data_bus,
    output [7:0] inst_address_bus
    );
    
    // Registers
    reg [7:0] r[3:0]; // Register Bank
    reg [7:0] pc;     // Program Counter to Program Memory
    reg [7:0] sp;     // Stack Pointer to Data Memory
    reg Z;  // Zero Flag
    reg C;  // Carry Bit
    reg N;  // Negative Flag
    reg V;  // Overflow Flag
    
    // Data Memory
    reg [7:0] mem [255:0];  // The memory implemented as an array
    
    // State Machine
    reg [2:0] state;
    
    // Special Registers
    reg [5:0] instruction;
    reg [1:0] ra;
    reg [1:0] rb;
    reg A7;
    reg B7;
    reg [7:0] result;
    
    wire [7:0]  in_port [3:0];
    reg  [7:0] out_port [3:0];
    
    // Signals and Wiring
    wire [5:0] cat1_opcode;
    wire [5:0] cat2_opcode;
    wire [1:0] cat1_ra;
    wire [1:0] cat1_rb;
    wire [1:0] cat2_ra;
    wire [7:0] argument;
    wire R7;
    
    wire [7:0] r0;     // These four signals
    wire [7:0] r1;     // make the cpu registers
    wire [7:0] r2;     // available as signals to
    wire [7:0] r3;     // the waveform simulator.
    assign r0 = r[0];  // This issue came un
    assign r1 = r[1];  // in EDAPlayground when 
    assign r2 = r[2];  // EDWave wouldn't show
    assign r3 = r[3];  // the registers as signals.
    
    assign inst_address_bus = pc;
    assign cat1_opcode = {2'b00,inst_data_bus[7:4]};
    assign cat2_opcode = inst_data_bus[7:2];
    assign cat1_ra = inst_data_bus[3:2];
    assign cat1_rb = inst_data_bus[1:0];
    assign cat2_ra = inst_data_bus[1:0];
    assign argument = inst_data_bus;
    assign R7 = result[7];
    assign  in_port[0] = in_port_0;
    assign  in_port[1] = in_port_1;
    assign  in_port[2] = in_port_2;
    assign  in_port[3] = in_port_3;
    assign out_port_0 = out_port[0];
    assign out_port_1 = out_port[1];
    assign out_port_2 = out_port[2];
    assign out_port_3 = out_port[3];
    
    wire [15:0] mult;
    assign mult  = r[rb] *r[ra];
    
    // Procedural Code
    
    always @(posedge(clk)) begin
        if (reset == 0) begin
            state <= `FETCH;
            pc    <= 8'b0000_0000;
            sp    <= 8'b1111_1111;
            in_strobe  <= 4'b1111; 
            out_strobe <= 4'b1111;
        end
        else begin
            case(state)
                `FETCH: begin
                    in_strobe  <= 4'b1111;
                    out_strobe <= 4'b1111;
                    if (inst_data_bus[7]==1'b0) begin // Instruction Category 
                        instruction <= cat1_opcode;   // Category 1
                        ra <= cat1_ra;
                        rb <= cat1_rb;
                    end
                    else begin                        // Category 2
                        instruction <= cat2_opcode;
                        ra <= cat2_ra;
                        case(cat2_opcode)
                            `LD_IMM,
                            `CMP_IMM, 
                            `BRA, 
                            `BHI,
                            `BEQ:  pc <= pc + 8'd1;
                        endcase
                    end
                    state <= `EXECUTE;
                end
                `EXECUTE: begin
                    case(instruction)
                        `ADD_REG: begin
                            result <= r[ra] + r[rb];
                            A7 <= r[ra][7];
                            B7 <= r[rb][7];
                            state <= `WRITE_BACK;
                        end
                        `MUL: begin
                            {r[rb],r[ra]} <= (ra==rb)?{mult[7:0],mult[7:0]}:(mult);
                            pc <= pc + 8'd1;
                            state <= `FETCH;
                        end      
                        `MOV: begin
                            r[ra] <= r[rb];
                            Z <= (r[rb]==8'd0)?1'b1:1'b0;
                            N <= r[rb][7];
                            V <= 0;
                            pc <= pc + 8'd1;
                            state <= `FETCH;
                        end
                        `NOP: begin
                            pc <= pc + 8'd1;
                            state <= `FETCH;
                        end
                        `LD_IMM: begin
                            r[ra] <= argument;
                            Z <= (argument==8'd0)?1'b1:1'b0;
                            N <= argument[7];
                            V <= 0;
                            pc <= pc + 8'd1;
                            state <= `FETCH;
                        end
                        `CMP_IMM: begin
                            result <= r[ra] - argument;
                            A7 <= r[ra][7];
                            B7 <= argument[7];
                            state <= `WRITE_BACK;
                        end
                        `DEC: begin
                            result <= r[ra] - 8'd1;
                            A7 <= r[ra][7];
                            state <= `WRITE_BACK;
                        end   
                        `INPUT: begin
                            r[ra] = in_port[ra];
                            state <= `WRITE_BACK;
                        end
                        `OUTPUT: begin
                            out_port[ra] = r[ra];
                            state <= `WRITE_BACK;
                        end                        
                        `BRA: begin
                            pc <= argument;
                            state <= `FETCH;
                        end                         
                        `BHI: begin          //   11111111 > 00000000
                            if(C==0 && Z==0) 
                                pc <= argument;
                            else
                                pc <= pc + 8'd1;
                            state <= `FETCH;
                        end
                        `BEQ: begin
                            if(Z==1) 
                                pc <= argument;
                            else
                                pc <= pc + 8'd1;
                            state <= `FETCH;
                         end 
                    endcase
                end
                `WRITE_BACK: begin
                    case(instruction)
                        `ADD_REG: begin
                            r[ra] <= result;
                            V <= (A7&B7&~R7)|(~A7&~B7&R7);
                            N <= R7;
                            Z <= (result==8'd0)?1'b1:1'b0;
                            C <= (A7&B7)|(B7&~R7)|(~R7&A7);
                        end
                        `CMP_IMM: begin
                            V <= (A7&~B7&~R7)|(~A7&B7&R7);
                            N <= R7;
                            Z <= (result==8'd0)?1'b1:1'b0;
                            C <= (~A7&B7)|(B7&R7)|(R7&~A7);
                        end
                        `DEC: begin
                            r[ra] <= result;
                            V <= ~R7&A7;
                            N <= R7;
                            Z <= (result==8'd0)?1'b1:1'b0;
                        end   
                        `INPUT: 
                            in_strobe[ra] = 1'b0;
                        `OUTPUT:
                            out_strobe[ra] = 1'b0;
                    endcase
                    pc <= pc + 8'd1;
                    state <= `FETCH;
                end
                default: begin
                    state <= `FETCH;
                    pc    <= 8'b0000_0000;
                    sp    <= 8'b1111_1111;
                    in_strobe  <= 4'b1111; 
                    out_strobe <= 4'b1111;
                end
            endcase
        end        
	end
endmodule

Vivado/Vivado.srcs/sim_1/new/testing_prog2.v
`timescale 1ns / 1ps
//////////////////////////////////////////////////////////////////////////////////
// Company: 
// Engineer: 
// 
// Create Date: 03/05/2023 06:17:14 PM
// Design Name: 
// Module Name: testing_prog2
// Project Name: 
// Target Devices: 
// Tool Versions: 
// Description: 
// 
// Dependencies: 
// 
// Revision:
// Revision 0.01 - File Created
// Additional Comments:
// 
//////////////////////////////////////////////////////////////////////////////////


module testing_prog2();
    reg clk;
    reg reset;
    wire [7:0] prog_data_bus;
    wire [7:0] prog_addr_bus;
    wire [3:0] S_strobe;
    wire [7:0] fib;
    reg [7:0] A;
    reg [7:0] S;
    
    mcp mcp2(
        .clk(clk),
        .reset(reset),
        .in_port_0(A),
        .out_port_1(fib),
        .out_strobe(S_strobe),
        .inst_data_bus(prog_data_bus),
        .inst_address_bus(prog_addr_bus)
    );
    
    program_memory2 pm(
        .address_bus(prog_addr_bus),
        .data_bus(prog_data_bus),
        .reset(reset),
        .program_clk(clk)
    );
    always #5 clk = !clk;

    always @ (negedge(S_strobe[1])) begin
      S <= fib;
      A <= A + 1;
    end
    
    initial begin
        $dumpfile("test.vcd"); 
        $dumpvars(0,testing_prog2); 
        clk <= 0;
        reset <= 1;
        A <= 0;
        S <= 0;
        #57;
        reset <= 0;
        #53;
        reset <= 1;
        #10507;
        $finish;
    end
endmodule

Vivado/Vivado.sim/sim_1/behav/xsim/test.vcd
$date
   Sun Mar  5 19:16:57 2023
$end
$version
  2022.2
$end
$timescale
  1ps
$end
$scope module testing_prog2 $end
$var reg 1 ! clk $end
$var reg 1 " reset $end
$var wire 8 # prog_data_bus [7:0] $end
$var wire 8 $ prog_addr_bus [7:0] $end
$var wire 4 % S_strobe [3:0] $end
$var wire 8 & fib [7:0] $end
$var reg 8 ' A [7:0] $end
$var reg 8 ( S [7:0] $end
$scope module mcp2 $end
$var wire 1 ) clk $end
$var wire 1 * reset $end
$var wire 8 + in_port_0 [7:0] $end
$var wire 8 , in_port_1 [7:0] $end
$var wire 8 - in_port_2 [7:0] $end
$var wire 8 . in_port_3 [7:0] $end
$var wire 8 / out_port_0 [7:0] $end
$var wire 8 & out_port_1 [7:0] $end
$var wire 8 0 out_port_2 [7:0] $end
$var wire 8 1 out_port_3 [7:0] $end
$var reg 4 2 in_strobe [3:0] $end
$var reg 4 3 out_strobe [3:0] $end
$var wire 8 # inst_data_bus [7:0] $end
$var wire 8 $ inst_address_bus [7:0] $end
$var reg 8 4 pc [7:0] $end
$var reg 8 5 sp [7:0] $end
$var reg 1 6 Z $end
$var reg 1 7 C $end
$var reg 1 8 N $end
$var reg 1 9 V $end
$var reg 3 : state [2:0] $end
$var reg 6 ; instruction [5:0] $end
$var reg 2 < ra [1:0] $end
$var reg 2 = rb [1:0] $end
$var reg 1 > A7 $end
$var reg 1 ? B7 $end
$var reg 8 @ result [7:0] $end
$var wire 6 A cat1_opcode [5:0] $end
$var wire 6 B cat2_opcode [5:0] $end
$var wire 2 C cat1_ra [1:0] $end
$var wire 2 D cat1_rb [1:0] $end
$var wire 2 E cat2_ra [1:0] $end
$var wire 8 F argument [7:0] $end
$var wire 1 G R7 $end
$var wire 8 H r0 [7:0] $end
$var wire 8 I r1 [7:0] $end
$var wire 8 J r2 [7:0] $end
$var wire 8 K r3 [7:0] $end
$var wire 16 L mult [15:0] $end
$upscope $end
$scope module pm $end
$var wire 8 $ address_bus [7:0] $end
$var wire 8 # data_bus [7:0] $end
$var wire 1 M reset $end
$var wire 1 N program_clk $end
$upscope $end
$upscope $end
$enddefinitions $end
#0
$dumpvars
0!
1"
bx #
bx $
bx %
bx &
b0 '
b0 (
0)
1*
b0 +
bz ,
bz -
bz .
bx /
bx 0
bx 1
bx 2
bx 3
bx 4
bx 5
x6
x7
x8
x9
bx :
bx ;
bx <
bx =
x>
x?
bx @
b0xxxx A
bx B
bx C
bx D
bx E
bx F
xG
bx H
bx I
bx J
bx K
bx L
1M
0N
$end
#5000
1!
bx #
b0 $
b1111 %
1)
b1111 2
b1111 3
b0 4
b11111111 5
b1 :
1N
#10000
0!
0)
0N
#15000
1!
1)
b1111 3
b10 :
1N
#20000
0!
0)
0N
#25000
1!
1)
1N
#30000
0!
0)
0N
#35000
1!
1)
1N
#40000
0!
0)
0N
#45000
1!
1)
1N
#50000
0!
0)
0N
#55000
1!
1)
1N
#57000
0"
0*
0M
#60000
0!
0)
0N
#65000
1!
b10011000 #
1)
b1111 3
b1 :
b1001 A
b100110 B
b10 C
b0 D
b0 E
b10011000 F
1N
#70000
0!
0)
0N
#75000
1!
1)
b1111 3
1N
#80000
0!
0)
0N
#85000
1!
1)
b1111 3
1N
#90000
0!
0)
0N
#95000
1!
1)
b1111 3
1N
#100000
0!
0)
0N
#105000
1!
1)
b1111 3
1N
#110000
0!
1"
0)
1*
1M
0N
#115000
1!
1)
b1111 3
b10 :
b100110 ;
b0 <
1N
#120000
0!
0)
0N
#125000
1!
1)
b100 :
b0 H
1N
#130000
0!
0)
0N
#135000
1!
b10001100 #
b1 $
1)
b1110 2
b1 4
b1 :
b1000 A
b100011 B
b11 C
b10001100 F
1N
#140000
0!
0)
0N
#145000
1!
b1 #
b10 $
1)
b1111 2
b1111 3
b10 4
b10 :
b100011 ;
b0 A
b0 B
b0 C
b1 D
b1 E
b1 F
1N
#150000
0!
0)
0N
#155000
1!
1)
b100 :
0>
0?
b11111111 @
1G
1N
#160000
0!
0)
0N
#165000
1!
b10110000 #
b11 $
1)
b11 4
06
17
18
09
b1 :
b1011 A
b101100 B
b0 D
b0 E
b10110000 F
1N
#170000
0!
0)
0N
#175000
1!
b1001 #
b100 $
1)
b1111 3
b100 4
b10 :
b101100 ;
b0 A
b10 B
b10 C
b1 D
b1 E
b1001 F
1N
#180000
0!
0)
0N
#185000
1!
b1000100 #
b101 $
1)
b101 4
b1 :
b100 A
b10001 B
b1 C
b0 D
b0 E
b1000100 F
1N
#190000
0!
0)
0N
#195000
1!
1)
b1111 3
b10 :
b100 ;
b1 <
b0 =
1N
#200000
0!
0)
0N
#205000
1!
b10011101 #
b110 $
1)
b110 4
16
08
b1 :
b1001 A
b100111 B
b11 C
b1 D
b1 E
b10011101 F
b0 I
b0 L
1N
#210000
0!
0)
0N
#215000
1!
1)
b1111 3
b10 :
b100111 ;
1N
#220000
0!
0)
0N
#225000
1!
b0 &
1)
b100 :
1N
#230000
0!
0)
0N
#235000
1!
b10101000 #
b111 $
b1101 %
b1 '
1)
b1 +
b1101 3
b111 4
b1 :
b1010 A
b101010 B
b10 C
b0 D
b0 E
b10101000 F
1N
#240000
0!
0)
0N
#245000
1!
b0 #
b1000 $
b1111 %
1)
b1111 3
b1000 4
b10 :
b101010 ;
b0 <
b0 A
b0 B
b0 C
b0 F
1N
#250000
0!
0)
0N
#255000
1!
b10011000 #
b0 $
1)
b0 4
b1 :
b1001 A
b100110 B
b10 C
b10011000 F
1N
#260000
0!
0)
0N
#265000
1!
1)
b1111 3
b10 :
b100110 ;
1N
#270000
0!
0)
0N
#275000
1!
1)
b100 :
b1 H
b1 L
1N
#280000
0!
0)
0N
#285000
1!
b10001100 #
b1 $
1)
b1110 2
b1 4
b1 :
b1000 A
b100011 B
b11 C
b10001100 F
1N
#290000
0!
0)
0N
#295000
1!
b1 #
b10 $
1)
b1111 2
b1111 3
b10 4
b10 :
b100011 ;
b0 A
b0 B
b0 C
b1 D
b1 E
b1 F
1N
#300000
0!
0)
0N
#305000
1!
1)
b100 :
b0 @
0G
1N
#310000
0!
0)
0N
#315000
1!
b10110000 #
b11 $
1)
b11 4
07
b1 :
b1011 A
b101100 B
b0 D
b0 E
b10110000 F
1N
#320000
0!
0)
0N
#325000
1!
b1001 #
b100 $
1)
b1111 3
b100 4
b10 :
b101100 ;
b0 A
b10 B
b10 C
b1 D
b1 E
b1001 F
1N
#330000
0!
0)
0N
#335000
1!
b1000100 #
b101 $
1)
b101 4
b1 :
b100 A
b10001 B
b1 C
b0 D
b0 E
b1000100 F
1N
#340000
0!
0)
0N
#345000
1!
1)
b1111 3
b10 :
b100 ;
b1 <
b0 L
1N
#350000
0!
0)
0N
#355000
1!
b10011101 #
b110 $
1)
b110 4
06
b1 :
b1001 A
b100111 B
b11 C
b1 D
b1 E
b10011101 F
b1 I
b1 L
1N
#360000
0!
0)
0N
#365000
1!
1)
b1111 3
b10 :
b100111 ;
1N
#370000
0!
0)
0N
#375000
1!
b1 &
1)
b100 :
1N
#380000
0!
0)
0N
#385000
1!
b10101000 #
b111 $
b1101 %
b10 '
b1 (
1)
b10 +
b1101 3
b111 4
b1 :
b1010 A
b101010 B
b10 C
b0 D
b0 E
b10101000 F
1N
#390000
0!
0)
0N
#395000
1!
b0 #
b1000 $
b1111 %
1)
b1111 3
b1000 4
b10 :
b101010 ;
b0 <
b0 A
b0 B
b0 C
b0 F
1N
#400000
0!
0)
0N
#405000
1!
b10011000 #
b0 $
1)
b0 4
b1 :
b1001 A
b100110 B
b10 C
b10011000 F
1N
#410000
0!
0)
0N
#415000
1!
1)
b1111 3
b10 :
b100110 ;
1N
#420000
0!
0)
0N
#425000
1!
1)
b100 :
b10 H
b100 L
1N
#430000
0!
0)
0N
#435000
1!
b10001100 #
b1 $
1)
b1110 2
b1 4
b1 :
b1000 A
b100011 B
b11 C
b10001100 F
1N
#440000
0!
0)
0N
#445000
1!
b1 #
b10 $
1)
b1111 2
b1111 3
b10 4
b10 :
b100011 ;
b0 A
b0 B
b0 C
b1 D
b1 E
b1 F
1N
#450000
0!
0)
0N
#455000
1!
1)
b100 :
b1 @
1N
#460000
0!
0)
0N
#465000
1!
b10110000 #
b11 $
1)
b11 4
b1 :
b1011 A
b101100 B
b0 D
b0 E
b10110000 F
1N
#470000
0!
0)
0N
#475000
1!
b1001 #
b100 $
1)
b1111 3
b100 4
b10 :
b101100 ;
b0 A
b10 B
b10 C
b1 D
b1 E
b1001 F
1N
#480000
0!
0)
0N
#485000
1!
b10000001 #
b1001 $
1)
b1001 4
b1 :
b1000 A
b100000 B
b0 C
b10000001 F
1N
#490000
0!
0)
0N
#495000
1!
b0 #
b1010 $
1)
b1111 3
b1010 4
b10 :
b100000 ;
b1 <
b0 A
b0 B
b0 D
b0 E
b0 F
b10 L
1N
#500000
0!
0)
0N
#505000
1!
b10000010 #
b1011 $
1)
b1011 4
16
b1 :
b1000 A
b100000 B
b10 D
b10 E
b10000010 F
b0 I
b0 L
1N
#510000
0!
0)
0N
#515000
1!
b1 #
b1100 $
1)
b1111 3
b1100 4
b10 :
b10 <
b0 A
b0 B
b1 D
b1 E
b1 F
bx L
1N
#520000
0!
0)
0N
#525000
1!
b10001100 #
b1101 $
1)
b1101 4
06
b1 :
b1000 A
b100011 B
b11 C
b0 D
b0 E
b10001100 F
b1 J
b10 L
1N
#530000
0!
0)
0N
#535000
1!
b0 #
b1110 $
1)
b1111 3
b1110 4
b10 :
b100011 ;
b0 <
b0 A
b0 B
b0 C
b0 F
b100 L
1N
#540000
0!
0)
0N
#545000
1!
1)
b100 :
b10 @
1N
#550000
0!
0)
0N
#555000
1!
b10110100 #
b1111 $
1)
b1111 4
b1 :
b1011 A
b101101 B
b1 C
b10110100 F
1N
#560000
0!
0)
0N
#565000
1!
b110 #
b10000 $
1)
b1111 3
b10000 4
b10 :
b101101 ;
b0 A
b1 B
b10 D
b10 E
b110 F
1N
#570000
0!
0)
0N
#575000
1!
b1001101 #
b10001 $
1)
b10001 4
b1 :
b100 A
b10011 B
b11 C
b1 D
b1 E
b1001101 F
1N
#580000
0!
0)
0N
#585000
1!
1)
b1111 3
b10 :
b100 ;
b11 <
b1 =
bx L
1N
#590000
0!
0)
0N
#595000
1!
b1110 #
b10010 $
1)
b10010 4
16
b1 :
b0 A
b11 B
b10 D
b10 E
b1110 F
b0 K
b0 L
1N
#600000
0!
0)
0N
#605000
1!
1)
b1111 3
b10 :
b0 ;
b10 =
1N
#610000
0!
0)
0N
#615000
1!
1)
b100 :
b1 @
1N
#620000
0!
0)
0N
#625000
1!
b1000110 #
b10011 $
1)
b10011 4
06
b1 :
b100 A
b10001 B
b1 C
b1000110 F
b1 K
b1 L
1N
#630000
0!
0)
0N
#635000
1!
1)
b1111 3
b10 :
b100 ;
b1 <
b0 L
1N
#640000
0!
0)
0N
#645000
1!
b1001011 #
b10100 $
1)
b10100 4
b1 :
b10010 B
b10 C
b11 D
b11 E
b1001011 F
b1 I
b1 L
1N
#650000
0!
0)
0N
#655000
1!
1)
b1111 3
b10 :
b10 <
b11 =
1N
#660000
0!
0)
0N
#665000
1!
b10010100 #
b10101 $
1)
b10101 4
b1 :
b1001 A
b100101 B
b1 C
b0 D
b0 E
b10010100 F
1N
#670000
0!
0)
0N
#675000
1!
1)
b1111 3
b10 :
b100101 ;
b0 <
b10 L
1N
#680000
0!
0)
0N
#685000
1!
1)
b100 :
1N
#690000
0!
0)
0N
#695000
1!
b10101000 #
b10110 $
1)
b10110 4
b1 :
b1010 A
b101010 B
b10 C
b10101000 F
b1 H
b1 L
1N
#700000
0!
0)
0N
#705000
1!
b1101 #
b10111 $
1)
b1111 3
b10111 4
b10 :
b101010 ;
b0 A
b11 B
b11 C
b1 D
b1 E
b1101 F
1N
#710000
0!
0)
0N
#715000
1!
b10001100 #
b1101 $
1)
b1101 4
b1 :
b1000 A
b100011 B
b0 D
b0 E
b10001100 F
1N
#720000
0!
0)
0N
#725000
1!
b0 #
b1110 $
1)
b1111 3
b1110 4
b10 :
b100011 ;
b0 A
b0 B
b0 C
b0 F
1N
#730000
0!
0)
0N
#735000
1!
1)
b100 :
1N
#740000
0!
0)
0N
#745000
1!
b10110100 #
b1111 $
1)
b1111 4
b1 :
b1011 A
b101101 B
b1 C
b10110100 F
1N
#750000
0!
0)
0N
#755000
1!
b110 #
b10000 $
1)
b1111 3
b10000 4
b10 :
b101101 ;
b0 A
b1 B
b10 D
b10 E
b110 F
1N
#760000
0!
0)
0N
#765000
1!
b1001101 #
b10001 $
1)
b10001 4
b1 :
b100 A
b10011 B
b11 C
b1 D
b1 E
b1001101 F
1N
#770000
0!
0)
0N
#775000
1!
1)
b1111 3
b10 :
b100 ;
b11 <
b1 =
1N
#780000
0!
0)
0N
#785000
1!
b1110 #
b10010 $
1)
b10010 4
b1 :
b0 A
b11 B
b10 D
b10 E
b1110 F
1N
#790000
0!
0)
0N
#795000
1!
1)
b1111 3
b10 :
b0 ;
b10 =
1N
#800000
0!
0)
0N
#805000
1!
1)
b100 :
b10 @
1N
#810000
0!
0)
0N
#815000
1!
b1000110 #
b10011 $
1)
b10011 4
b1 :
b100 A
b10001 B
b1 C
b1000110 F
b10 K
b10 L
1N
#820000
0!
0)
0N
#825000
1!
1)
b1111 3
b10 :
b100 ;
b1 <
b1 L
1N
#830000
0!
0)
0N
#835000
1!
b1001011 #
b10100 $
1)
b10100 4
b1 :
b10010 B
b10 C
b11 D
b11 E
b1001011 F
1N
#840000
0!
0)
0N
#845000
1!
1)
b1111 3
b10 :
b10 <
b11 =
b10 L
1N
#850000
0!
0)
0N
#855000
1!
b10010100 #
b10101 $
1)
b10101 4
b1 :
b1001 A
b100101 B
b1 C
b0 D
b0 E
b10010100 F
b10 J
b100 L
1N
#860000
0!
0)
0N
#865000
1!
1)
b1111 3
b10 :
b100101 ;
b0 <
b10 L
1N
#870000
0!
0)
0N
#875000
1!
1)
b100 :
b0 @
1N
#880000
0!
0)
0N
#885000
1!
b10101000 #
b10110 $
1)
b10110 4
16
b1 :
b1010 A
b101010 B
b10 C
b10101000 F
b0 H
b0 L
1N
#890000
0!
0)
0N
#895000
1!
b1101 #
b10111 $
1)
b1111 3
b10111 4
b10 :
b101010 ;
b0 A
b11 B
b11 C
b1 D
b1 E
b1101 F
1N
#900000
0!
0)
0N
#905000
1!
b10001100 #
b1101 $
1)
b1101 4
b1 :
b1000 A
b100011 B
b0 D
b0 E
b10001100 F
1N
#910000
0!
0)
0N
#915000
1!
b0 #
b1110 $
1)
b1111 3
b1110 4
b10 :
b100011 ;
b0 A
b0 B
b0 C
b0 F
1N
#920000
0!
0)
0N
#925000
1!
1)
b100 :
1N
#930000
0!
0)
0N
#935000
1!
b10110100 #
b1111 $
1)
b1111 4
b1 :
b1011 A
b101101 B
b1 C
b10110100 F
1N
#940000
0!
0)
0N
#945000
1!
b110 #
b10000 $
1)
b1111 3
b10000 4
b10 :
b101101 ;
b0 A
b1 B
b10 D
b10 E
b110 F
1N
#950000
0!
0)
0N
#955000
1!
b10011101 #
b110 $
1)
b110 4
b1 :
b1001 A
b100111 B
b11 C
b1 D
b1 E
b10011101 F
1N
#960000
0!
0)
0N
#965000
1!
1)
b1111 3
b10 :
b100111 ;
b1 <
b10 L
1N
#970000
0!
0)
0N
#975000
1!
1)
b100 :
1N
#980000
0!
0)
0N
#985000
1!
b10101000 #
b111 $
b1101 %
b11 '
1)
b11 +
b1101 3
b111 4
b1 :
b1010 A
b101010 B
b10 C
b0 D
b0 E
b10101000 F
1N
#990000
0!
0)
0N
#995000
1!
b0 #
b1000 $
b1111 %
1)
b1111 3
b1000 4
b10 :
b101010 ;
b0 <
b0 A
b0 B
b0 C
b0 F
b0 L
1N
#1000000
0!
0)
0N
#1005000
1!
b10011000 #
b0 $
1)
b0 4
b1 :
b1001 A
b100110 B
b10 C
b10011000 F
1N
#1010000
0!
0)
0N
#1015000
1!
1)
b1111 3
b10 :
b100110 ;
1N
#1020000
0!
0)
0N
#1025000
1!
1)
b100 :
b11 H
b110 L
1N
#1030000
0!
0)
0N
#1035000
1!
b10001100 #
b1 $
1)
b1110 2
b1 4
b1 :
b1000 A
b100011 B
b11 C
b10001100 F
1N
#1040000
0!
0)
0N
#1045000
1!
b1 #
b10 $
1)
b1111 2
b1111 3
b10 4
b10 :
b100011 ;
b0 A
b0 B
b0 C
b1 D
b1 E
b1 F
1N
#1050000
0!
0)
0N
#1055000
1!
1)
b100 :
b10 @
1N
#1060000
0!
0)
0N
#1065000
1!
b10110000 #
b11 $
1)
b11 4
06
b1 :
b1011 A
b101100 B
b0 D
b0 E
b10110000 F
1N
#1070000
0!
0)
0N
#1075000
1!
b1001 #
b100 $
1)
b1111 3
b100 4
b10 :
b101100 ;
b0 A
b10 B
b10 C
b1 D
b1 E
b1001 F
1N
#1080000
0!
0)
0N
#1085000
1!
b10000001 #
b1001 $
1)
b1001 4
b1 :
b1000 A
b100000 B
b0 C
b10000001 F
1N
#1090000
0!
0)
0N
#1095000
1!
b0 #
b1010 $
1)
b1111 3
b1010 4
b10 :
b100000 ;
b1 <
b0 A
b0 B
b0 D
b0 E
b0 F
b10 L
1N
#1100000
0!
0)
0N
#1105000
1!
b10000010 #
b1011 $
1)
b1011 4
16
b1 :
b1000 A
b100000 B
b10 D
b10 E
b10000010 F
b0 I
b0 L
1N
#1110000
0!
0)
0N
#1115000
1!
b1 #
b1100 $
1)
b1111 3
b1100 4
b10 :
b10 <
b0 A
b0 B
b1 D
b1 E
b1 F
b100 L
1N
#1120000
0!
0)
0N
#1125000
1!
b10001100 #
b1101 $
1)
b1101 4
06
b1 :
b1000 A
b100011 B
b11 C
b0 D
b0 E
b10001100 F
b1 J
b10 L
1N
#1130000
0!
0)
0N
#1135000
1!
b0 #
b1110 $
1)
b1111 3
b1110 4
b10 :
b100011 ;
b0 <
b0 A
b0 B
b0 C
b0 F
b110 L
1N
#1140000
0!
0)
0N
#1145000
1!
1)
b100 :
b11 @
1N
#1150000
0!
0)
0N
#1155000
1!
b10110100 #
b1111 $
1)
b1111 4
b1 :
b1011 A
b101101 B
b1 C
b10110100 F
1N
#1160000
0!
0)
0N
