Vivado/Vivado.srcs/sources_1/new/program_memory1.v
`timescale 1ns / 1ps
//////////////////////////////////////////////////////////////////////////////////
// Company: 
// Engineer: 
// 
// Create Date: 03/05/2023 04:39:44 PM
// Design Name: 
// Module Name: program_memory
// Project Name: 
// Target Devices: 
// Tool Versions: 
// Description: 
// 
// Dependencies: 
// 
// Revision:
// Revision 0.01 - File Created
// Additional Comments:
// 
//////////////////////////////////////////////////////////////////////////////////

// Opcodes
`define OP_ADD      4'b0000
`define OP_MUL      4'b0010
`define OP_MOV      4'b0100
`define OP_NOP      4'b0111
`define OP_LD_IMM   6'b100000
`define OP_CMP_IMM  6'b100011
`define OP_DEC      6'b100101
`define OP_INPUT    6'b100110
`define OP_OUTPUT   6'b100111
`define OP_BRA      6'b101010
`define OP_BHI      6'b101100
`define OP_BEQ      6'b101101

module program_memory1(
    input  [7:0] address_bus,
    output [7:0] data_bus,
    input  reset,
    input program_clk
    );
    
    reg [7:0] program_rom [255:0];
    assign data_bus = program_rom[address_bus];
    
    always @(posedge(program_clk))
        if (reset == 0) begin
            program_rom[ 0] <= {`OP_INPUT,2'b00};       //start:  INPUT R0
            program_rom[ 1] <= {`OP_INPUT,2'b01};       //        INPUT R1
            program_rom[ 2] <= {`OP_ADD,2'b00,2'b01};   //        ADD R0, R1
            program_rom[ 3] <= {`OP_OUTPUT,2'b00};      //        OUTPUT R0
            program_rom[ 4] <= {`OP_BRA,2'b00};         //        BRA start (0x00) 
            program_rom[ 5] <= 8'b0000_0000;            //        ^^^ start = 0x00
            program_rom[ 6] <= 8'b0111_0000; // NOP
            program_rom[ 7] <= 8'b0111_0000; // NOP
            program_rom[ 8] <= 8'b0111_0000; // NOP
            program_rom[ 9] <= 8'b0111_0000; // NOP
            program_rom[10] <= 8'b0111_0000; // NOP
            program_rom[11] <= 8'b0111_0000; // NOP
            program_rom[12] <= 8'b0111_0000; // NOP
            program_rom[13] <= 8'b0111_0000; // NOP
            program_rom[14] <= 8'b0111_0000; // NOP
            program_rom[15] <= 8'b0111_0000; // NOP
            program_rom[16] <= 8'b0111_0000; // NOP
            program_rom[17] <= 8'b0111_0000; // NOP
            program_rom[18] <= 8'b0111_0000; // NOP
            program_rom[19] <= 8'b0111_0000; // NOP
            program_rom[20] <= 8'b0111_0000; // NOP
            program_rom[21] <= 8'b0111_0000; // NOP
            program_rom[22] <= 8'b0111_0000; // NOP
            program_rom[23] <= 8'b0111_0000; // NOP
            program_rom[24] <= 8'b0111_0000; // NOP
            program_rom[25] <= 8'b0111_0000; // NOP
            program_rom[26] <= 8'b0111_0000; // NOP
            program_rom[27] <= 8'b0111_0000; // NOP
            program_rom[28] <= 8'b0111_0000; // NOP
            program_rom[29] <= 8'b0111_0000; // NOP
            program_rom[30] <= 8'b0111_0000; // NOP
            program_rom[31] <= 8'b0111_0000; // NOP
     end
endmodule

Vivado/Vivado.srcs/sources_1/new/MCP.v
`timescale 1ns / 1ps
//////////////////////////////////////////////////////////////////////////////////
// Company: 
// Engineer: Le Phu Thuan
// 
// Create Date: 03/05/2023 03:06:46 PM
// Design Name: 
// Module Name: mcp
// Project Name: Simple Microprocessor
// Target Devices: Basys3
// Tool Versions: Vivado 2022.2
// Description: 
// 
// Dependencies: 
// 
// Revision:
// Revision 0.01 - File Created
// Additional Comments:
// 
//////////////////////////////////////////////////////////////////////////////////

// Opcodes
`define ADD_REG  6'b000000
`define MUL      6'b000010
`define MOV      6'b000100
`define NOP      6'b000111
`define LD_IMM   6'b100000
`define CMP_IMM  6'b100011
`define DEC      6'b100101
`define INPUT    6'b100110
`define OUTPUT   6'b100111
`define BRA      6'b101010
`define BHI      6'b101100
`define BEQ      6'b101101

// Control Logic States, One-Hot Encoded
`define FETCH      3'b001
`define EXECUTE    3'b010
`define WRITE_BACK 3'b100

module mcp(
    input clk,
    input reset,
    input  [7:0]  in_port_0,
    input  [7:0]  in_port_1,
    input  [7:0]  in_port_2,
    input  [7:0]  in_port_3,
    output [7:0] out_port_0,
    output [7:0] out_port_1,
    output [7:0] out_port_2,
    output [7:0] out_port_3,
    output reg [3:0] in_strobe,
    output reg [3:0] out_strobe,
    input  [7:0] inst_data_bus,
    output [7:0] inst_address_bus
    );
    
    // Registers
    reg [7:0] r[3:0]; // Register Bank
    reg [7:0] pc;     // Program Counter to Program Memory
    reg [7:0] sp;     // Stack Pointer to Data Memory
    reg Z;  // Zero Flag
    reg C;  // Carry Bit
    reg N;  // Negative Flag
    reg V;  // Overflow Flag
    
    // Data Memory
    reg [7:0] mem [255:0];  // The memory implemented as an array
    
    // State Machine
    reg [2:0] state;
    
    // Special Registers
    reg [5:0] instruction;
    reg [1:0] ra;
    reg [1:0] rb;
    reg A7;
    reg B7;
    reg [7:0] result;
    
    wire [7:0]  in_port [3:0];
    reg  [7:0] out_port [3:0];
    
    // Signals and Wiring
    wire [5:0] cat1_opcode;
    wire [5:0] cat2_opcode;
    wire [1:0] cat1_ra;
    wire [1:0] cat1_rb;
    wire [1:0] cat2_ra;
    wire [7:0] argument;
    wire R7;
    
    wire [7:0] r0;     // These four signals
    wire [7:0] r1;     // make the cpu registers
    wire [7:0] r2;     // available as signals to
    wire [7:0] r3;     // the waveform simulator.
    assign r0 = r[0];  // This issue came un
    assign r1 = r[1];  // in EDAPlayground when 
    assign r2 = r[2];  // EDWave wouldn't show
    assign r3 = r[3];  // the registers as signals.
    
    assign inst_address_bus = pc;
    assign cat1_opcode = {2'b00,inst_data_bus[7:4]};
    assign cat2_opcode = inst_data_bus[7:2];
    assign cat1_ra = inst_data_bus[3:2];
    assign cat1_rb = inst_data_bus[1:0];
    assign cat2_ra = inst_data_bus[1:0];
    assign argument = inst_data_bus;
    assign R7 = result[7];
    assign  in_port[0] = in_port_0;
    assign  in_port[1] = in_port_1;
    assign  in_port[2] = in_port_2;
    assign  in_port[3] = in_port_3;
    assign out_port_0 = out_port[0];
    assign out_port_1 = out_port[1];
    assign out_port_2 = out_port[2];
    assign out_port_3 = out_port[3];
    
    wire [15:0] mult;
    assign mult  = r[rb] *r[ra];
    
    // Procedural Code
    
    always @(posedge(clk)) begin
        if (reset == 0) begin
            state <= `FETCH;
            pc    <= 8'b0000_0000;
            sp    <= 8'b1111_1111;
            in_strobe  <= 4'b1111; 
            out_strobe <= 4'b1111;
        end
        else begin
            case(state)
                `FETCH: begin
                    in_strobe  <= 4'b1111;
                    out_strobe <= 4'b1111;
                    if (inst_data_bus[7]==1'b0) begin // Instruction Category 
                        instruction <= cat1_opcode;   // Category 1
                        ra <= cat1_ra;
                        rb <= cat1_rb;
                    end
                    else begin                        // Category 2
                        instruction <= cat2_opcode;
                        ra <= cat2_ra;
                        case(cat2_opcode)
                            `LD_IMM,
                            `CMP_IMM, 
                            `BRA, 
                            `BHI,
                            `BEQ:  pc <= pc + 8'd1;
                        endcase
                    end
                    state <= `EXECUTE;
                end
                `EXECUTE: begin
                    case(instruction)
                        `ADD_REG: begin
                            result <= r[ra] + r[rb];
                            A7 <= r[ra][7];
                            B7 <= r[rb][7];
                            state <= `WRITE_BACK;
                        end
                        `MUL: begin
                            {r[rb],r[ra]} <= (ra==rb)?{mult[7:0],mult[7:0]}:(mult);
                            pc <= pc + 8'd1;
                            state <= `FETCH;
                        end      
                        `MOV: begin
                            r[ra] <= r[rb];
                            Z <= (r[rb]==8'd0)?1'b1:1'b0;
                            N <= r[rb][7];
                            V <= 0;
                            pc <= pc + 8'd1;
                            state <= `FETCH;
                        end
                        `NOP: begin
                            pc <= pc + 8'd1;
                            state <= `FETCH;
                        end
                        `LD_IMM: begin
                            r[ra] <= argument;
                            Z <= (argument==8'd0)?1'b1:1'b0;
                            N <= argument[7];
                            V <= 0;
                            pc <= pc + 8'd1;
                            state <= `FETCH;
                        end
                        `CMP_IMM: begin
                            result <= r[ra] - argument;
                            A7 <= r[ra][7];
                            B7 <= argument[7];
                            state <= `WRITE_BACK;
                        end
                        `DEC: begin
                            result <= r[ra] - 8'd1;
                            A7 <= r[ra][7];
                            state <= `WRITE_BACK;
                        end   
                        `INPUT: begin
                            r[ra] = in_port[ra];
                            state <= `WRITE_BACK;
                        end
                        `OUTPUT: begin
                            out_port[ra] = r[ra];
                            state <= `WRITE_BACK;
                        end                        
                        `BRA: begin
                            pc <= argument;
                            state <= `FETCH;
                        end                         
                        `BHI: begin          //   11111111 > 00000000
                            if(C==0 && Z==0) 
                                pc <= argument;
                            else
                                pc <= pc + 8'd1;
                            state <= `FETCH;
                        end
                        `BEQ: begin
                            if(Z==1) 
                                pc <= argument;
                            else
                                pc <= pc + 8'd1;
                            state <= `FETCH;
                         end 
                    endcase
                end
                `WRITE_BACK: begin
                    case(instruction)
                        `ADD_REG: begin
                            r[ra] <= result;
                            V <= (A7&B7&~R7)|(~A7&~B7&R7);
                            N <= R7;
                            Z <= (result==8'd0)?1'b1:1'b0;
                            C <= (A7&B7)|(B7&~R7)|(~R7&A7);
                        end
                        `CMP_IMM: begin
                            V <= (A7&~B7&~R7)|(~A7&B7&R7);
                            N <= R7;
                            Z <= (result==8'd0)?1'b1:1'b0;
                            C <= (~A7&B7)|(B7&R7)|(R7&~A7);
                        end
                        `DEC: begin
                            r[ra] <= result;
                            V <= ~R7&A7;
                            N <= R7;
                            Z <= (result==8'd0)?1'b1:1'b0;
                        end   
                        `INPUT: 
                            in_strobe[ra] = 1'b0;
                        `OUTPUT:
                            out_strobe[ra] = 1'b0;
                    endcase
                    pc <= pc + 8'd1;
                    state <= `FETCH;
                end
                default: begin
                    state <= `FETCH;
                    pc    <= 8'b0000_0000;
                    sp    <= 8'b1111_1111;
                    in_strobe  <= 4'b1111; 
                    out_strobe <= 4'b1111;
                end
            endcase
        end        
	end
endmodule

Vivado/Vivado.srcs/sim_1/new/testing_prog1.v
`timescale 1ns / 1ps
//////////////////////////////////////////////////////////////////////////////////
// Company: 
// Engineer: 
// 
// Create Date: 03/05/2023 06:16:24 PM
// Design Name: 
// Module Name: testing_prog1
// Project Name: 
// Target Devices: 
// Tool Versions: 
// Description: 
// 
// Dependencies: 
// 
// Revision:
// Revision 0.01 - File Created
// Additional Comments:
// 
//////////////////////////////////////////////////////////////////////////////////


module testing_prog1();
    reg clk;
    reg reset;
    wire [7:0] prog_data_bus;
    wire [7:0] prog_addr_bus;
    wire [3:0] S_strobe;
    wire [7:0] sum;
    reg [7:0] A;
    reg [7:0] B;
    reg [7:0] S;
    
    mcp mcp1(
        .clk(clk),
        .reset(reset),
        .in_port_0(A),
        .in_port_1(B),
        .out_port_0(sum),
        .out_strobe(S_strobe),
        .inst_data_bus(prog_data_bus),
        .inst_address_bus(prog_addr_bus)
    );
    
    program_memory1 pm(
        .address_bus(prog_addr_bus),
        .data_bus(prog_data_bus),
        .reset(reset),
        .program_clk(clk)
    );
    always #5 clk = !clk;

    always @ (negedge(S_strobe[0])) begin
      S <= sum;
    end
    
    initial begin
        $dumpfile("test.vcd"); 
        $dumpvars(0,testing_prog1); 
        clk <= 0;
        reset <= 1;
        A <= 0;
        B <= 0;
        S <= 0;
        #50;
        reset <= 0;
        #50;
        reset <= 1;
        #400;
        A <= 2;
        B <= 3;
        #400;
        A <= 21;
        B <= 100;
        #400;
        $finish;
    end
    
endmodule

Vivado/Vivado.sim/sim_1/behav/xsim/test.vcd
$date
   Sun Mar  5 19:03:55 2023
$end
$version
  2022.2
$end
$timescale
  1ps
$end
$scope module testing_prog1 $end
$var reg 1 ! clk $end
$var reg 1 " reset $end
$var wire 8 # prog_data_bus [7:0] $end
$var wire 8 $ prog_addr_bus [7:0] $end
$var wire 4 % S_strobe [3:0] $end
$var wire 8 & sum [7:0] $end
$var reg 8 ' A [7:0] $end
$var reg 8 ( B [7:0] $end
$var reg 8 ) S [7:0] $end
$scope module mcp1 $end
$var wire 1 * clk $end
$var wire 1 + reset $end
$var wire 8 , in_port_0 [7:0] $end
$var wire 8 - in_port_1 [7:0] $end
$var wire 8 . in_port_2 [7:0] $end
$var wire 8 / in_port_3 [7:0] $end
$var wire 8 & out_port_0 [7:0] $end
$var wire 8 0 out_port_1 [7:0] $end
$var wire 8 1 out_port_2 [7:0] $end
$var wire 8 2 out_port_3 [7:0] $end
$var reg 4 3 in_strobe [3:0] $end
$var reg 4 4 out_strobe [3:0] $end
$var wire 8 # inst_data_bus [7:0] $end
$var wire 8 $ inst_address_bus [7:0] $end
$var reg 8 5 pc [7:0] $end
$var reg 8 6 sp [7:0] $end
$var reg 1 7 Z $end
$var reg 1 8 C $end
$var reg 1 9 N $end
$var reg 1 : V $end
$var reg 3 ; state [2:0] $end
$var reg 6 < instruction [5:0] $end
$var reg 2 = ra [1:0] $end
$var reg 2 > rb [1:0] $end
$var reg 1 ? A7 $end
$var reg 1 @ B7 $end
$var reg 8 A result [7:0] $end
$var wire 6 B cat1_opcode [5:0] $end
$var wire 6 C cat2_opcode [5:0] $end
$var wire 2 D cat1_ra [1:0] $end
$var wire 2 E cat1_rb [1:0] $end
$var wire 2 F cat2_ra [1:0] $end
$var wire 8 G argument [7:0] $end
$var wire 1 H R7 $end
$var wire 8 I r0 [7:0] $end
$var wire 8 J r1 [7:0] $end
$var wire 8 K r2 [7:0] $end
$var wire 8 L r3 [7:0] $end
$var wire 16 M mult [15:0] $end
$upscope $end
$scope module pm $end
$var wire 8 $ address_bus [7:0] $end
$var wire 8 # data_bus [7:0] $end
$var wire 1 N reset $end
$var wire 1 O program_clk $end
$upscope $end
$upscope $end
$enddefinitions $end
#0
$dumpvars
0!
1"
bx #
bx $
bx %
bx &
b0 '
b0 (
b0 )
0*
1+
b0 ,
b0 -
bz .
bz /
bx 0
bx 1
bx 2
bx 3
bx 4
bx 5
bx 6
x7
x8
x9
x:
bx ;
bx <
bx =
bx >
x?
x@
bx A
b0xxxx B
bx C
bx D
bx E
bx F
bx G
xH
bx I
bx J
bx K
bx L
bx M
1N
0O
$end
#5000
1!
bx #
b0 $
b1111 %
1*
b1111 3
b1111 4
b0 5
b11111111 6
b1 ;
1O
#10000
0!
0*
0O
#15000
1!
1*
b1111 4
b10 ;
1O
#20000
0!
0*
0O
#25000
1!
1*
1O
#30000
0!
0*
0O
#35000
1!
1*
1O
#40000
0!
0*
0O
#45000
1!
1*
1O
#50000
0!
0"
0*
0+
0N
0O
#55000
1!
b10011000 #
1*
b1111 4
b1 ;
b1001 B
b100110 C
b10 D
b0 E
b0 F
b10011000 G
1O
#60000
0!
0*
0O
#65000
1!
1*
b1111 4
1O
#70000
0!
0*
0O
#75000
1!
1*
b1111 4
1O
#80000
0!
0*
0O
#85000
1!
1*
b1111 4
1O
#90000
0!
0*
0O
#95000
1!
1*
b1111 4
1O
#100000
0!
1"
0*
1+
1N
0O
#105000
1!
1*
b1111 4
b10 ;
b100110 <
b0 =
1O
#110000
0!
0*
0O
#115000
1!
1*
b100 ;
b0 I
1O
#120000
0!
0*
0O
#125000
1!
b10011001 #
b1 $
1*
b1110 3
b1 5
b1 ;
b1 E
b1 F
b10011001 G
1O
#130000
0!
0*
0O
#135000
1!
1*
b1111 3
b1111 4
b10 ;
b1 =
1O
#140000
0!
0*
0O
#145000
1!
1*
b100 ;
b0 J
1O
#150000
0!
0*
0O
#155000
1!
b1 #
b10 $
1*
b1101 3
b10 5
b1 ;
b0 B
b0 C
b0 D
b1 G
1O
#160000
0!
0*
0O
#165000
1!
1*
b1111 3
b1111 4
b10 ;
b0 <
b0 =
b1 >
b0 M
1O
#170000
0!
0*
0O
#175000
1!
1*
b100 ;
0?
0@
b0 A
0H
1O
#180000
0!
0*
0O
#185000
1!
b10011100 #
b11 $
1*
b11 5
17
08
09
0:
b1 ;
b1001 B
b100111 C
b11 D
b0 E
b0 F
b10011100 G
1O
#190000
0!
0*
0O
#195000
1!
1*
b1111 4
b10 ;
b100111 <
1O
#200000
0!
0*
0O
#205000
1!
b0 &
1*
b100 ;
1O
#210000
0!
0*
0O
#215000
1!
b10101000 #
b100 $
b1110 %
1*
b1110 4
b100 5
b1 ;
b1010 B
b101010 C
b10 D
b10101000 G
1O
#220000
0!
0*
0O
#225000
1!
b0 #
b101 $
b1111 %
1*
b1111 4
b101 5
b10 ;
b101010 <
b0 B
b0 C
b0 D
b0 G
1O
#230000
0!
0*
0O
#235000
1!
b10011000 #
b0 $
1*
b0 5
b1 ;
b1001 B
b100110 C
b10 D
b10011000 G
1O
#240000
0!
0*
0O
#245000
1!
1*
b1111 4
b10 ;
b100110 <
1O
#250000
0!
0*
0O
#255000
1!
1*
b100 ;
1O
#260000
0!
0*
0O
#265000
1!
b10011001 #
b1 $
1*
b1110 3
b1 5
b1 ;
b1 E
b1 F
b10011001 G
1O
#270000
0!
0*
0O
#275000
1!
1*
b1111 3
b1111 4
b10 ;
b1 =
1O
#280000
0!
0*
0O
#285000
1!
1*
b100 ;
1O
#290000
0!
0*
0O
#295000
1!
b1 #
b10 $
1*
b1101 3
b10 5
b1 ;
b0 B
b0 C
b0 D
b1 G
1O
#300000
0!
0*
0O
#305000
1!
1*
b1111 3
b1111 4
b10 ;
b0 <
b0 =
1O
#310000
0!
0*
0O
#315000
1!
1*
b100 ;
1O
#320000
0!
0*
0O
#325000
1!
b10011100 #
b11 $
1*
b11 5
b1 ;
b1001 B
b100111 C
b11 D
b0 E
b0 F
b10011100 G
1O
#330000
0!
0*
0O
#335000
1!
1*
b1111 4
b10 ;
b100111 <
1O
#340000
0!
0*
0O
#345000
1!
1*
b100 ;
1O
#350000
0!
0*
0O
#355000
1!
b10101000 #
b100 $
b1110 %
1*
b1110 4
b100 5
b1 ;
b1010 B
b101010 C
b10 D
b10101000 G
1O
#360000
0!
0*
0O
#365000
1!
b0 #
b101 $
b1111 %
1*
b1111 4
b101 5
b10 ;
b101010 <
b0 B
b0 C
b0 D
b0 G
1O
#370000
0!
0*
0O
#375000
1!
b10011000 #
b0 $
1*
b0 5
b1 ;
b1001 B
b100110 C
b10 D
b10011000 G
1O
#380000
0!
0*
0O
#385000
1!
1*
b1111 4
b10 ;
b100110 <
1O
#390000
0!
0*
0O
#395000
1!
1*
b100 ;
1O
#400000
0!
0*
0O
#405000
1!
b10011001 #
b1 $
1*
b1110 3
b1 5
b1 ;
b1 E
b1 F
b10011001 G
1O
#410000
0!
0*
0O
#415000
1!
1*
b1111 3
b1111 4
b10 ;
b1 =
1O
#420000
0!
0*
0O
#425000
1!
1*
b100 ;
1O
#430000
0!
0*
0O
#435000
1!
b1 #
b10 $
1*
b1101 3
b10 5
b1 ;
b0 B
b0 C
b0 D
b1 G
1O
#440000
0!
0*
0O
#445000
1!
1*
b1111 3
b1111 4
b10 ;
b0 <
b0 =
1O
#450000
0!
0*
0O
#455000
1!
1*
b100 ;
1O
#460000
0!
0*
0O
#465000
1!
b10011100 #
b11 $
1*
b11 5
b1 ;
b1001 B
b100111 C
b11 D
b0 E
b0 F
b10011100 G
1O
#470000
0!
0*
0O
#475000
1!
1*
b1111 4
b10 ;
b100111 <
1O
#480000
0!
0*
0O
#485000
1!
1*
b100 ;
1O
#490000
0!
0*
0O
#495000
1!
b10101000 #
b100 $
b1110 %
1*
b1110 4
b100 5
b1 ;
b1010 B
b101010 C
b10 D
b10101000 G
1O
#500000
0!
b10 '
b11 (
0*
b10 ,
b11 -
0O
#505000
1!
b0 #
b101 $
b1111 %
1*
b1111 4
b101 5
b10 ;
b101010 <
b0 B
b0 C
b0 D
b0 G
1O
#510000
0!
0*
0O
#515000
1!
b10011000 #
b0 $
1*
b0 5
b1 ;
b1001 B
b100110 C
b10 D
b10011000 G
1O
#520000
0!
0*
0O
#525000
1!
1*
b1111 4
b10 ;
b100110 <
1O
#530000
0!
0*
0O
#535000
1!
1*
b100 ;
b10 I
1O
#540000
0!
0*
0O
#545000
1!
b10011001 #
b1 $
1*
b1110 3
b1 5
b1 ;
b1 E
b1 F
b10011001 G
1O
#550000
0!
0*
0O
#555000
1!
1*
b1111 3
b1111 4
b10 ;
b1 =
1O
#560000
0!
0*
0O
#565000
1!
1*
b100 ;
b11 J
b1001 M
1O
#570000
0!
0*
0O
#575000
1!
b1 #
b10 $
1*
b1101 3
b10 5
b1 ;
b0 B
b0 C
b0 D
b1 G
1O
#580000
0!
0*
0O
#585000
1!
1*
b1111 3
b1111 4
b10 ;
b0 <
b0 =
b110 M
1O
#590000
0!
0*
0O
#595000
1!
1*
b100 ;
b101 A
1O
#600000
0!
0*
0O
#605000
1!
b10011100 #
b11 $
1*
b11 5
07
b1 ;
b1001 B
b100111 C
b11 D
b0 E
b0 F
b10011100 G
b101 I
b1111 M
1O
#610000
0!
0*
0O
#615000
1!
1*
b1111 4
b10 ;
b100111 <
1O
#620000
0!
0*
0O
#625000
1!
b101 &
1*
b100 ;
1O
#630000
0!
0*
0O
#635000
1!
b10101000 #
b100 $
b1110 %
b101 )
1*
b1110 4
b100 5
b1 ;
b1010 B
b101010 C
b10 D
b10101000 G
1O
#640000
0!
0*
0O
#645000
1!
b0 #
b101 $
b1111 %
1*
b1111 4
b101 5
b10 ;
b101010 <
b0 B
b0 C
b0 D
b0 G
1O
#650000
0!
0*
0O
#655000
1!
b10011000 #
b0 $
1*
b0 5
b1 ;
b1001 B
b100110 C
b10 D
b10011000 G
1O
#660000
0!
0*
0O
#665000
1!
1*
b1111 4
b10 ;
b100110 <
1O
#670000
0!
0*
0O
#675000
1!
1*
b100 ;
b10 I
b110 M
1O
#680000
0!
0*
0O
#685000
1!
b10011001 #
b1 $
1*
b1110 3
b1 5
b1 ;
b1 E
b1 F
b10011001 G
1O
#690000
0!
0*
0O
#695000
1!
1*
b1111 3
b1111 4
b10 ;
b1 =
b1001 M
1O
#700000
0!
0*
0O
#705000
1!
1*
b100 ;
1O
#710000
0!
0*
0O
#715000
1!
b1 #
b10 $
1*
b1101 3
b10 5
b1 ;
b0 B
b0 C
b0 D
b1 G
1O
#720000
0!
0*
0O
#725000
1!
1*
b1111 3
b1111 4
b10 ;
b0 <
b0 =
b110 M
1O
#730000
0!
0*
0O
#735000
1!
1*
b100 ;
1O
#740000
0!
0*
0O
#745000
1!
b10011100 #
b11 $
1*
b11 5
b1 ;
b1001 B
b100111 C
b11 D
b0 E
b0 F
b10011100 G
b101 I
b1111 M
1O
#750000
0!
0*
0O
#755000
1!
1*
b1111 4
b10 ;
b100111 <
1O
#760000
0!
0*
0O
#765000
1!
1*
b100 ;
1O
#770000
0!
0*
0O
#775000
1!
b10101000 #
b100 $
b1110 %
1*
b1110 4
b100 5
b1 ;
b1010 B
b101010 C
b10 D
b10101000 G
1O
#780000
0!
0*
0O
#785000
1!
b0 #
b101 $
b1111 %
1*
b1111 4
b101 5
b10 ;
b101010 <
b0 B
b0 C
b0 D
b0 G
1O
#790000
0!
0*
0O
#795000
1!
b10011000 #
b0 $
1*
b0 5
b1 ;
b1001 B
b100110 C
b10 D
b10011000 G
1O
#800000
0!
0*
0O
#805000
1!
1*
b1111 4
b10 ;
b100110 <
1O
#810000
0!
0*
0O
#815000
1!
1*
b100 ;
b10 I
b110 M
1O
#820000
0!
0*
0O
#825000
1!
b10011001 #
b1 $
1*
b1110 3
b1 5
b1 ;
b1 E
b1 F
b10011001 G
1O
#830000
0!
0*
0O
#835000
1!
1*
b1111 3
b1111 4
b10 ;
b1 =
b1001 M
1O
#840000
0!
0*
0O
#845000
1!
1*
b100 ;
1O
#850000
0!
0*
0O
#855000
1!
b1 #
b10 $
1*
b1101 3
b10 5
b1 ;
b0 B
b0 C
b0 D
b1 G
1O
#860000
0!
0*
0O
#865000
1!
1*
b1111 3
b1111 4
b10 ;
b0 <
b0 =
b110 M
1O
#870000
0!
0*
0O
#875000
1!
1*
b100 ;
1O
#880000
0!
0*
0O
#885000
1!
b10011100 #
b11 $
1*
b11 5
b1 ;
b1001 B
b100111 C
b11 D
b0 E
b0 F
b10011100 G
b101 I
b1111 M
1O
#890000
0!
0*
0O
#895000
1!
1*
b1111 4
b10 ;
b100111 <
1O
#900000
0!
b10101 '
b1100100 (
0*
b10101 ,
b1100100 -
0O
#905000
1!
1*
b100 ;
1O
#910000
0!
0*
0O
#915000
1!
b10101000 #
b100 $
b1110 %
1*
b1110 4
b100 5
b1 ;
b1010 B
b101010 C
b10 D
b10101000 G
1O
#920000
0!
0*
0O
#925000
1!
b0 #
b101 $
b1111 %
1*
b1111 4
b101 5
b10 ;
b101010 <
b0 B
b0 C
b0 D
b0 G
1O
#930000
0!
0*
0O
#935000
1!
b10011000 #
b0 $
1*
b0 5
b1 ;
b1001 B
b100110 C
b10 D
b10011000 G
1O
#940000
0!
0*
0O
#945000
1!
1*
b1111 4
b10 ;
b100110 <
1O
#950000
0!
0*
0O
#955000
1!
1*
b100 ;
b10101 I
b111111 M
1O
#960000
0!
0*
0O
#965000
1!
b10011001 #
b1 $
1*
b1110 3
b1 5
b1 ;
b1 E
b1 F
b10011001 G
1O
#970000
0!
0*
0O
#975000
1!
1*
b1111 3
b1111 4
b10 ;
b1 =
b1001 M
1O
#980000
0!
0*
0O
#985000
1!
1*
b100 ;
b1100100 J
b10011100010000 M
1O
#990000
0!
0*
0O
#995000
1!
b1 #
b10 $
1*
b1101 3
b10 5
b1 ;
b0 B
b0 C
b0 D
b1 G
1O
#1000000
0!
0*
0O
#1005000
1!
1*
b1111 3
b1111 4
b10 ;
b0 <
b0 =
b100000110100 M
1O
#1010000
0!
0*
0O
#1015000
1!
1*
b100 ;
b1111001 A
1O
#1020000
0!
0*
0O
#1025000
1!
b10011100 #
b11 $
1*
b11 5
b1 ;
b1001 B
b100111 C
b11 D
b0 E
b0 F
b10011100 G
b1111001 I
b10111101000100 M
1O
#1030000
0!
0*
0O
#1035000
1!
1*
b1111 4
b10 ;
b100111 <
1O
#1040000
0!
0*
0O
#1045000
1!
b1111001 &
1*
b100 ;
1O
#1050000
0!
0*
0O
#1055000
1!
b10101000 #
b100 $
b1110 %
b1111001 )
1*
b1110 4
b100 5
b1 ;
b1010 B
b101010 C
b10 D
b10101000 G
1O
#1060000
0!
0*
0O
#1065000
1!
b0 #
b101 $
b1111 %
1*
b1111 4
b101 5
b10 ;
b101010 <
b0 B
b0 C
b0 D
b0 G
1O
#1070000
0!
0*
0O
#1075000
1!
b10011000 #
b0 $
1*
b0 5
b1 ;
b1001 B
b100110 C
b10 D
b10011000 G
1O
#1080000
0!
0*
0O
#1085000
1!
1*
b1111 4
b10 ;
b100110 <
1O
#1090000
0!
0*
0O
#1095000
1!
1*
b100 ;
b10101 I
b100000110100 M
1O
#1100000
0!
0*
0O
#1105000
1!
b10011001 #
b1 $
1*
b1110 3
b1 5
b1 ;
b1 E
b1 F
b10011001 G
1O
#1110000
0!
0*
0O
#1115000
1!
1*
b1111 3
b1111 4
b10 ;
b1 =
b10011100010000 M
1O
#1120000
0!
0*
0O
#1125000
1!
1*
b100 ;
1O
#1130000
0!
0*
0O
#1135000
1!
b1 #
b10 $
1*
b1101 3
b10 5
b1 ;
b0 B
b0 C
b0 D
b1 G
1O
#1140000
0!
0*
0O
#1145000
1!
1*
b1111 3
b1111 4
b10 ;
b0 <
b0 =
b100000110100 M
1O
#1150000
0!
0*
0O
#1155000
1!
1*
b100 ;
1O
#1160000
0!
0*
0O
#1165000
1!
b10011100 #
b11 $
1*
b11 5
b1 ;
b1001 B
b100111 C
b11 D
b0 E
b0 F
b10011100 G
b1111001 I
b10111101000100 M
1O
#1170000
0!
0*
0O
#1175000
1!
1*
b1111 4
b10 ;
b100111 <
1O
#1180000
0!
0*
0O
#1185000
1!
1*
b100 ;
1O
#1190000
0!
0*
0O
#1195000
1!
b10101000 #
b100 $
b1110 %
1*
b1110 4
b100 5
b1 ;
b1010 B
b101010 C
b10 D
b10101000 G
1O
#1200000
0!
0*
0O
#1205000
1!
b0 #
b101 $
b1111 %
1*
b1111 4
b101 5
b10 ;
b101010 <
b0 B
b0 C
b0 D
b0 G
1O
#1210000
0!
0*
0O
#1215000
1!
b10011000 #
b0 $
1*
b0 5
b1 ;
b1001 B
b100110 C
b10 D
b10011000 G
1O
#1220000
0!
0*
0O
#1225000
1!
1*
b1111 4
b10 ;
b100110 <
1O
#1230000
0!
0*
0O
#1235000
1!
1*
b100 ;
b10101 I
b100000110100 M
1O
#1240000
0!
0*
0O
#1245000
1!
b10011001 #
b1 $
1*
b1110 3
b1 5
b1 ;
b1 E
b1 F
b10011001 G
1O
#1250000
0!
0*
0O
#1255000
1!
1*
b1111 3
b1111 4
b10 ;
b1 =
b10011100010000 M
1O
#1260000
0!
0*
0O
#1265000
1!
1*
b100 ;
1O
#1270000
0!
0*
0O
#1275000
1!
b1 #
b10 $
1*
b1101 3
b10 5
b1 ;
b0 B
b0 C
b0 D
b1 G
1O
#1280000
0!
0*
0O
#1285000
1!
1*
b1111 3
b1111 4
b10 ;
b0 <
b0 =
b100000110100 M
1O
